nanoiso/__init__.py
nanoiso/main.py
nanoiso/modules/__init__.py
nanoiso/modules/map.py
nanoiso/scripts/plot.R
nanoiso/static/env.yaml
nanoiso/utils/__init__.py
nanoiso/utils/minimap2.py
nanoiso-0.1.0.dist-info/METADATA
nanoiso-0.1.0.dist-info/WHEEL
nanoiso-0.1.0.dist-info/RECORD
